clickhouse_df/__init__.py
clickhouse_df/dtype.py
clickhouse_df/parse.py
clickhouse_df/thread_utils.py
clickhouse_df/yck.py
clickhouse_df-0.1.5.dist-info/licenses/LICENSE
clickhouse_df-0.1.5.dist-info/METADATA
clickhouse_df-0.1.5.dist-info/WHEEL
clickhouse_df-0.1.5.dist-info/top_level.txt
clickhouse_df-0.1.5.dist-info/RECORD
