Metadata-Version: 2.4
Name: clickhouse-df
Version: 0.1.5
Summary: Read ClickHouse Cluster Data To Pandas/Polars DataFrame
License: MIT License
Project-URL: homepage, https://github.com/link-yundi/clickhouse-df
Project-URL: repository, https://github.com/link-yundi/clickhouse-df
Requires-Python: >=3.9
License-File: LICENSE
Requires-Dist: clickhouse-driver>=0.2.9
Requires-Dist: pandas>=2.2.3
Requires-Dist: polars>=1.30.0
Requires-Dist: pyarrow<20.0.0
Requires-Dist: sqlparse>=0.5.3
Dynamic: license-file
